CONTRIBUTORS.rst
LICENSE.rst
MANIFEST.in
README.rst
requirements.txt
setup.py
domain_models/__init__.py
domain_models/__init__.pyc
domain_models/collections.py
domain_models/collections.pyc
domain_models/errors.py
domain_models/errors.pyc
domain_models/fields.py
domain_models/fields.pyc
domain_models/models.py
domain_models/models.pyc
domain_models/views.py
domain_models/views.pyc
domain_models.egg-info/PKG-INFO
domain_models.egg-info/SOURCES.txt
domain_models.egg-info/dependency_links.txt
domain_models.egg-info/pbr.json
domain_models.egg-info/requires.txt
domain_models.egg-info/top_level.txt
domain_models.egg-info/zip-safe