Metadata-Version: 1.1
Name: domain-models
Version: 0.0.9
Summary: Domain models framework for Python projects
Home-page: https://github.com/ets-labs/python-domain-models
Author: ETS Labs
Author-email: rmogilatov@gmail.com
License: BSD New
Download-URL: https://pypi.python.org/pypi/domain_models
Keywords: Domain models,Domain modelling,Domain driven design,Domain driven development,DDD,Models
Platform: any
Classifier: Development Status :: 2 - Pre-Alpha
Classifier: Intended Audience :: Developers
Classifier: License :: OSI Approved :: BSD License
Classifier: Operating System :: OS Independent
Classifier: Programming Language :: Python
Classifier: Programming Language :: Python :: 2
Classifier: Programming Language :: Python :: 2.6
Classifier: Programming Language :: Python :: 2.7
Classifier: Programming Language :: Python :: 3
Classifier: Programming Language :: Python :: 3.3
Classifier: Programming Language :: Python :: 3.4
Classifier: Programming Language :: Python :: 3.5
Classifier: Programming Language :: Python :: Implementation :: CPython
Classifier: Programming Language :: Python :: Implementation :: PyPy
Classifier: Topic :: Software Development
Classifier: Topic :: Software Development :: Libraries
Classifier: Topic :: Software Development :: Libraries :: Python Modules
